mkdocs_git_committers_plugin_2/__init__.py
mkdocs_git_committers_plugin_2/exclude.py
mkdocs_git_committers_plugin_2/plugin.py
mkdocs_git_committers_plugin_2-2.4.1.dist-info/LICENSE
mkdocs_git_committers_plugin_2-2.4.1.dist-info/METADATA
mkdocs_git_committers_plugin_2-2.4.1.dist-info/WHEEL
mkdocs_git_committers_plugin_2-2.4.1.dist-info/entry_points.txt
mkdocs_git_committers_plugin_2-2.4.1.dist-info/top_level.txt
mkdocs_git_committers_plugin_2-2.4.1.dist-info/RECORD
