Metadata-Version: 2.1
Name: mkdocs-git-committers-plugin-2
Version: 2.4.1
Summary: An MkDocs plugin to create a list of contributors on the page. The git-committers plugin will seed the template context with a list of GitHub or GitLab committers and other useful GIT info such as last modified date
Home-page: https://github.com/ojacques/mkdocs-git-committers-plugin-2/
Author: Byrne Reese, Olivier Jacques
Author-email: byrne@majordojo.com, ojacques2@gmail.com
License: MIT
Keywords: mkdocs,plugin,github,committers
Classifier: Development Status :: 4 - Beta
Classifier: Intended Audience :: Developers
Classifier: Intended Audience :: Information Technology
Classifier: License :: OSI Approved :: MIT License
Classifier: Programming Language :: Python
Classifier: Programming Language :: Python :: 3 :: Only
Classifier: Programming Language :: Python :: 3.8
Classifier: Programming Language :: Python :: 3.9
Classifier: Programming Language :: Python :: 3.10
Classifier: Programming Language :: Python :: 3.11
Requires-Python: >=3.8,<4
License-File: LICENSE
Requires-Dist: mkdocs>=1.0.3
Requires-Dist: requests
Requires-Dist: gitpython
